lndb_bfx_pipeline/__init__.py
lndb_bfx_pipeline/_core.py
lndb_bfx_pipeline/_schema.py
lndb_bfx_pipeline/schema.py
lndb_bfx_pipeline-0.1.0.dist-info/LICENSE
lndb_bfx_pipeline-0.1.0.dist-info/WHEEL
lndb_bfx_pipeline-0.1.0.dist-info/METADATA
lndb_bfx_pipeline-0.1.0.dist-info/RECORD
